synint.py
synint-0.2.4.dist-info/LICENSE.txt
synint-0.2.4.dist-info/METADATA
synint-0.2.4.dist-info/WHEEL
synint-0.2.4.dist-info/top_level.txt
synint-0.2.4.dist-info/RECORD
